{
  "transactions": [
    {
      "name": "Help Desk Dashboard",
      "type": "income",
      "amount": 2700,
      "id": 2
    },
    {
      "name": "borua shop",
      "type": "expense",
      "amount": 700,
      "id": 3
    },
    {
      "name": "chu debt",
      "type": "expense",
      "amount": 140,
      "id": 5
    },
    {
      "name": "dipto vai",
      "type": "expense",
      "amount": 1000,
      "id": 6
    },
    {
      "name": "adi bikrampur sweets",
      "type": "income",
      "amount": 16000,
      "id": 7
    },
    {
      "name": "joy vai",
      "type": "expense",
      "amount": 8500,
      "id": 8
    }
  ]
}